checkarchivedataset/__init__.py
checkarchivedataset/checkarchivedataset.py
checkarchivedataset-0.1.0.dist-info/METADATA
checkarchivedataset-0.1.0.dist-info/WHEEL
checkarchivedataset-0.1.0.dist-info/top_level.txt
checkarchivedataset-0.1.0.dist-info/RECORD
