Metadata-Version: 2.1
Name: checkarchivedataset
Version: 0.1.0
Summary: check archive dataset
Home-page: 
Author: lily
Author-email: 2239041944@qq.com
License: MIT
